pypi_demo/__init__.py
pypi_demo/np_arr_test.py
pypi_demo/np_arr_test_dev.py
pypi_pubpack_vin10-0.4.0.dist-info/METADATA
pypi_pubpack_vin10-0.4.0.dist-info/WHEEL
pypi_pubpack_vin10-0.4.0.dist-info/RECORD
